timethese.py
timethese-0.0.7.dist-info/AUTHORS.rst
timethese-0.0.7.dist-info/LICENSE
timethese-0.0.7.dist-info/METADATA
timethese-0.0.7.dist-info/WHEEL
timethese-0.0.7.dist-info/top_level.txt
timethese-0.0.7.dist-info/RECORD
