Metadata-Version: 2.1
Name: timethese
Version: 0.0.7
Summary: timeit for multiple functions with better reporting
Home-page: https://github.com/jwbargsten/python-timethese
Author: Joachim W. Bargsten
Author-email: jw@bargsten.org
License: MIT
Project-URL: Issue Tracker, https://github.com/jwbargsten/python-timethese/issues
Platform: UNKNOWN
Classifier: Development Status :: 5 - Production/Stable
Classifier: Intended Audience :: Developers
Classifier: License :: OSI Approved :: MIT License
Classifier: Operating System :: Unix
Classifier: Operating System :: POSIX
Classifier: Operating System :: Microsoft :: Windows
Classifier: Programming Language :: Python
Classifier: Programming Language :: Python :: 3
Classifier: Programming Language :: Python :: 3.5
Classifier: Programming Language :: Python :: 3.6
Classifier: Programming Language :: Python :: 3.7
Classifier: Programming Language :: Python :: 3.8
Classifier: Programming Language :: Python :: Implementation :: CPython
Classifier: Programming Language :: Python :: Implementation :: PyPy
Classifier: Topic :: Utilities
Requires-Python: >=3.5
Requires-Dist: more-itertools (>=8.2.0)
